snu_dhc/__init__.py
snu_dhc/tables.py
snu_dhc/statistics/__init__.py
snu_dhc/statistics/auc_ci_delong.py
snu_dhc/statistics/classification_ci_wilson.py
snu_dhc/statistics/utils.py
snu_dhc-0.1.8.dist-info/METADATA
snu_dhc-0.1.8.dist-info/WHEEL
snu_dhc-0.1.8.dist-info/top_level.txt
snu_dhc-0.1.8.dist-info/RECORD
