Metadata-Version: 2.4
Name: snu_dhc
Version: 0.1.8
Summary: SNU_DHC Package
Author: Dong Hyun Choi
Author-email: donghyun369@naver.com
Classifier: Programming Language :: Python :: 3
Classifier: License :: OSI Approved :: MIT License
Requires-Python: >=3.6
Dynamic: author
Dynamic: author-email
Dynamic: classifier
Dynamic: description
Dynamic: description-content-type
Dynamic: requires-python
Dynamic: summary
